logstashLog/__init__.py
logstashLog/logstash_log.py
logstashLog-1.0.0.dist-info/METADATA
logstashLog-1.0.0.dist-info/WHEEL
logstashLog-1.0.0.dist-info/top_level.txt
logstashLog-1.0.0.dist-info/RECORD
